weeb_cli/__init__.py
weeb_cli/__main__.py
weeb_cli/config.py
weeb_cli/i18n.py
weeb_cli/main.py
weeb_cli/commands/downloads.py
weeb_cli/commands/search.py
weeb_cli/commands/settings.py
weeb_cli/commands/setup.py
weeb_cli/commands/watchlist.py
weeb_cli/locales/en.json
weeb_cli/locales/tr.json
weeb_cli/providers/__init__.py
weeb_cli/providers/allanime.py
weeb_cli/providers/animecix.py
weeb_cli/providers/anizle.py
weeb_cli/providers/base.py
weeb_cli/providers/hianime.py
weeb_cli/providers/registry.py
weeb_cli/providers/turkanime.py
weeb_cli/providers/extractors/__init__.py
weeb_cli/providers/extractors/megacloud.py
weeb_cli/services/__init__.py
weeb_cli/services/database.py
weeb_cli/services/dependency_manager.py
weeb_cli/services/details.py
weeb_cli/services/discord_rpc.py
weeb_cli/services/downloader.py
weeb_cli/services/local_library.py
weeb_cli/services/logger.py
weeb_cli/services/notifier.py
weeb_cli/services/player.py
weeb_cli/services/progress.py
weeb_cli/services/scraper.py
weeb_cli/services/search.py
weeb_cli/services/shortcuts.py
weeb_cli/services/tracker.py
weeb_cli/services/updater.py
weeb_cli/services/watch.py
weeb_cli/ui/__init__.py
weeb_cli/ui/header.py
weeb_cli/ui/menu.py
weeb_cli/ui/prompt.py
weeb_cli-2.5.0.dist-info/licenses/LICENSE
weeb_cli-2.5.0.dist-info/METADATA
weeb_cli-2.5.0.dist-info/WHEEL
weeb_cli-2.5.0.dist-info/entry_points.txt
weeb_cli-2.5.0.dist-info/top_level.txt
weeb_cli-2.5.0.dist-info/RECORD
