Metadata-Version: 2.4
Name: weeb-cli
Version: 2.5.0
Summary: Tarayıcı yok, reklam yok, dikkat dağıtıcı unsur yok. Sadece siz ve eşsiz bir anime izleme deneyimi.
Author-email: ewgsta <ewgst@proton.me>
License-Expression: CC-BY-NC-ND-4.0
Project-URL: Homepage, https://weeb-cli.ewgsta.me
Project-URL: Repository, https://github.com/ewgsta/weeb-cli
Project-URL: Issues, https://github.com/ewgsta/weeb-cli/issues
Keywords: anime,weeb,anime-download,anizm,anime-watch,anime-watching,anime-downloading,anime-cli,allanime,animecix,anime-indir,anime-izle,weeb-cli,anime-izleme,anime-indirme,weebanime,tranime
Classifier: Programming Language :: Python :: 3
Classifier: Operating System :: OS Independent
Classifier: Environment :: Console
Requires-Python: >=3.8
License-File: LICENSE
Requires-Dist: typer[all]
Requires-Dist: rich
Requires-Dist: questionary
Requires-Dist: requests
Requires-Dist: packaging
Requires-Dist: pycryptodome
Requires-Dist: curl_cffi
Requires-Dist: appdirs
Requires-Dist: prompt_toolkit<3.0.50,>=3.0.36
Requires-Dist: beautifulsoup4
Requires-Dist: lxml
Requires-Dist: py7zr
Requires-Dist: pypresence
Requires-Dist: winotify; sys_platform == "win32"
Dynamic: license-file
